mcp_pandoc/__init__.py
mcp_pandoc/server.py
mseep_mcp_pandoc-0.8.2.dist-info/licenses/LICENSE
mseep_mcp_pandoc-0.8.2.dist-info/METADATA
mseep_mcp_pandoc-0.8.2.dist-info/WHEEL
mseep_mcp_pandoc-0.8.2.dist-info/entry_points.txt
mseep_mcp_pandoc-0.8.2.dist-info/top_level.txt
mseep_mcp_pandoc-0.8.2.dist-info/RECORD
